stripe_traveller/__init__.py
stripe_traveller/traveller.py
stripe_traveller-2.0.0.dist-info/LICENSE
stripe_traveller-2.0.0.dist-info/METADATA
stripe_traveller-2.0.0.dist-info/WHEEL
stripe_traveller-2.0.0.dist-info/RECORD
