Metadata-Version: 2.1
Name: stripe-traveller
Version: 2.0.0
Summary: Wraps the Stripe Test Clock object for easier async/await-based test functions.
License: GNU LGPL v2.1
Author: Tyler Eon
Requires-Python: >=3.10,<4.0
Classifier: Development Status :: 5 - Production/Stable
Classifier: License :: Other/Proprietary License
Classifier: Programming Language :: Python :: 3
Classifier: Programming Language :: Python :: 3.10
Classifier: Programming Language :: Python :: 3.11
Classifier: Programming Language :: Python :: 3.12
Classifier: Topic :: Software Development :: Testing
Requires-Dist: stripe (>=6.1.0)
